labctl/__init__.py
labctl/__main__.py
labctl/commands/__init__.py
labctl/commands/admin/__init__.py
labctl/commands/admin/quota.py
labctl/commands/admin/users.py
labctl/commands/admin/vpn.py
labctl/commands/config.py
labctl/commands/devices.py
labctl/commands/project.py
labctl/commands/quota.py
labctl/core/__init__.py
labctl/core/api.py
labctl/core/config.py
labctl/core/console.py
labctl/core/decorators.py
labctl/main.py
labctl-0.7.0.dist-info/METADATA
labctl-0.7.0.dist-info/WHEEL
labctl-0.7.0.dist-info/entry_points.txt
labctl-0.7.0.dist-info/RECORD
